Metadata-Version: 2.1
Name: discordwebhook_v2
Version: 1.0.0
Summary: discordwebhook is a python library         for discord webhook with discord rest api on Python 3.6 and above.
Home-page: https://github.com/klemonade/discord-webhook-python
Author: klemonade
License: MIT
Keywords: discord webhook api python
Classifier: Development Status :: 5 - Production/Stable
Classifier: Programming Language :: Python
Classifier: Programming Language :: Python :: 3
Classifier: Programming Language :: Python :: 3.6
Classifier: Programming Language :: Python :: 3.7
Classifier: Programming Language :: Python :: 3.8
Classifier: Programming Language :: Python :: 3.9
Classifier: Intended Audience :: Developers
Classifier: Topic :: Communications :: Chat
Classifier: Topic :: System :: Networking
Classifier: Topic :: Office/Business
Classifier: License :: OSI Approved :: MIT License
Requires-Python: >=3.6.0
License-File: LICENSE.txt
Requires-Dist: requests
